molinfo/__init__.py
molinfo/app.py
molinfo/config/__init__.py
molinfo/config/constants.py
molinfo/config/setting.py
molinfo/data/__init__.py
molinfo/docs/__init__.py
molinfo/docs/chemgraphs.py
molinfo/docs/compound.py
molinfo/docs/compute.py
molinfo/docs/customchemgraph.py
molinfo/docs/element.py
molinfo/docs/graph3d.py
molinfo/docs/molparser.py
molinfo/docs/netwrok.py
molinfo/docs/observer.py
molinfo/docs/structure.py
molinfo/docs/utility.py
Molinfo-1.5.4.dist-info/LICENSE
Molinfo-1.5.4.dist-info/METADATA
Molinfo-1.5.4.dist-info/WHEEL
Molinfo-1.5.4.dist-info/top_level.txt
Molinfo-1.5.4.dist-info/RECORD
