Metadata-Version: 2.1
Name: Molinfo
Version: 1.5.4
Summary: Molinfo provides comprehensive molecular information and analysis.
Author: Sina Gilassi
Author-email: <sina.gilassi@gmail.com>
License: MIT
Keywords: python,chemistry,chemistry-visualization,Molinfo,molecular-graph
Classifier: Development Status :: 1 - Planning
Classifier: Intended Audience :: Education
Classifier: Programming Language :: Python :: 3
Classifier: Operating System :: Unix
Classifier: Operating System :: MacOS :: MacOS X
Classifier: Operating System :: Microsoft :: Windows
Requires-Python: >=3.6
License-File: LICENSE
Requires-Dist: pandas
Requires-Dist: pillow
Requires-Dist: requests
Requires-Dist: urllib3
Requires-Dist: matplotlib
Requires-Dist: PubChemQuery
Requires-Dist: numpy
Requires-Dist: plotly
Requires-Dist: networkx
